Workbook
Name calc_annual_div: Inputs!$D$24
Name drv_capex_pct_rev: Inputs!$I$35:$R$35
Name drv_da_pct_capex: Inputs!$I$36:$R$36
Name drv_exit_multiple: Inputs!$I$37:$R$37
Name drv_gross_margin: Inputs!$I$32:$R$32
Name drv_opex_pct_rev: Inputs!$I$33:$R$33
Name drv_revenue_growth: Inputs!$I$31:$R$31
Name inp_annual_dps: Inputs!$D$13
Name inp_cash: Inputs!$D$16
Name inp_cash_sweep_pct: Inputs!$D$20
Name inp_company_name: Inputs!$D$8
Name inp_currency: Inputs!$D$10
Name inp_current_price: Inputs!$D$11
Name inp_debt: Inputs!$D$17
Name inp_diluted_shares: Inputs!$D$12
Name inp_dps_growth: Inputs!$D$14
Name inp_equity_investments: Inputs!$D$19
Name inp_fye_month: Inputs!$D$7
Name inp_min_cash: Inputs!$D$21
Name inp_minority_interest: Inputs!$D$18
Name inp_run_date: Inputs!$D$6
Name inp_sector: Inputs!$D$9
Name inp_tax_rate: Inputs!$D$15
Name inp_ticker: Inputs!$D$5
Name IQ_CH: 110000
Name IQ_CQ: 5000
Name IQ_CY: 10000
Name IQ_DAILY: 500000
Name IQ_FH: 100000
Name IQ_FQ: 500
Name IQ_FY: 1000
Name IQ_LTM: 2000
Name IQ_MONTH: 15000
Name IQ_NTM: 6000
Name IQ_WEEK: 50000
Name IQ_YTD: 3000
Name mkt_cap: Inputs!$D$25
Name sens_target_year_offset: Sensitivity!$C$4

Sheet Cover
B2: =inp_ticker & " | Cover" -> APPL | Cover
B4: Company Name | C4: =inp_company_name -> Apple Inc.
B5: Ticker | C5: =inp_ticker -> APPL
B6: Sector | C6: =inp_sector -> Information Technology
B7: Currency | C7: =inp_currency -> USD
B8: Run Date | C8: =inp_run_date -> 46140
B9: Current Price | C9: =inp_current_price -> 267.61
B10: Market Cap | C10: =mkt_cap -> 3928819.9

Sheet Inputs
B2: =inp_ticker & " | Inputs & Assumptions" -> APPL | Inputs & Assumptions
B4: Inputs
B5: Ticker | D5: APPL
B6: Run Date | D6: 46140
B7: Fiscal Year End Month | D7: 12
B8: Company Name | D8: =_CapIQ_Data!F12 -> Apple Inc.
B9: Sector | D9: =_CapIQ_Data!F13 -> Information Technology
B10: Currency | D10: =_CapIQ_Data!F14 -> USD
B11: Current Price | D11: =_CapIQ_Data!F18 -> 267.61
B12: Diluted Shares Outstanding | D12: =_CapIQ_Data!F19 -> 14681.14
B13: Annual DPS | D13: =IFERROR(_CapIQ_Data!E40, _CapIQ_Data!D40) -> 1.02
B14: DPS Annual Growth % | D14: 0
B15: Tax Rate | D15: 0.27
B16: Cash & Equivalents | D16: =_CapIQ_Data!F21 -> 45317
B17: Total Debt | D17: =_CapIQ_Data!F23 -> 90509
B18: Minority Interest | D18: =_CapIQ_Data!F25 -> 0
B19: Equity Investments | D19: =_CapIQ_Data!F26 -> 0
B20: Cash Sweep % | D20: 0
B21: Minimum Cash Balance | D21: 0
B23: Calculated
B24: Annual Dividends Paid (current) | D24: =inp_annual_dps*inp_diluted_shares -> 14974.763
B25: Current Market Cap | D25: =inp_current_price*inp_diluted_shares -> 3928819.9
B26: Net Debt | D26: =inp_debt-inp_cash -> 45192
B27: Current Enterprise Value | D27: =mkt_cap+inp_debt-inp_cash+inp_minority_interest-inp_equity_investments -> 3974011.9
B29: Driver Assumptions (manual fill)
F30: 2023A | G30: 2024A | H30: 2025A | I30: 2026E | J30: 2027E | K30: 2028E | L30: 2029E | M30: 2030E | N30: 2031E | O30: 2032E | P30: 2033E | Q30: 2034E | R30: 2035E
B31: Revenue % Revenue | G31: =IS!D8 -> 0.020219941 | H31: =IS!E8 -> 0.064255118 | I31: 0.05 | J31: 0.05 | K31: 0.05 | L31: 0.05 | M31: 0.05 | N31: 0.05 | O31: 0.05 | P31: 0.05 | Q31: 0.05 | R31: 0.05
B32: % Gross Margin | F32: =IS!C12 -> 0.4413113 | G32: =IS!D12 -> 0.4620635 | H32: =IS!E12 -> 0.46905164 | I32: 0.4 | J32: 0.4 | K32: 0.4 | L32: 0.4 | M32: 0.4 | N32: 0.4 | O32: 0.4 | P32: 0.4 | Q32: 0.4 | R32: 0.4
B33: Cash Opex % Growth | G33: =IS!D18 -> 0.062176883 | H33: =IS!E18 -> 0.09628004 | I33: 0.1 | J33: 0.1 | K33: 0.1 | L33: 0.1 | M33: 0.1 | N33: 0.1 | O33: 0.1 | P33: 0.1 | Q33: 0.1 | R33: 0.1
B34: SBC % Cash Opex | F34: =IS!C27 -> 0.25002308 | G34: =IS!D27 -> 0.25396549 | H34: =IS!E27 -> 0.25495015 | I34: 0.25 | J34: 0.25 | K34: 0.25 | L34: 0.25 | M34: 0.25 | N34: 0.25 | O34: 0.25 | P34: 0.25 | Q34: 0.25 | R34: 0.25
B35: Capex % Revenue | F35: =IS!C47 -> 0.028592301 | G35: =IS!D47 -> 0.024158963 | H35: =IS!E47 -> 0.030553079 | I35: 0.03 | J35: 0.03 | K35: 0.03 | L35: 0.03 | M35: 0.03 | N35: 0.03 | O35: 0.03 | P35: 0.03 | Q35: 0.03 | R35: 0.03
B36: D&A % Capex | F36: =IS!C25 -> 1.0510996 | G36: =IS!D25 -> 1.2114957 | H36: =IS!E25 -> 0.92001573 | I36: 1 | J36: 1 | K36: 1 | L36: 1 | M36: 1 | N36: 1 | O36: 1 | P36: 1 | Q36: 1 | R36: 1
B37: Exit EBITDA Multiple | I37: 10 | J37: 10 | K37: 10 | L37: 10 | M37: 10 | N37: 10 | O37: 10 | P37: 10 | Q37: 10 | R37: 10

Sheet IS
B2: =inp_ticker & " | Income Statement" -> APPL | Income Statement
C4: Actual | F4: Forecast
C5: 2023A | D5: 2024A | E5: 2025A | F5: 2026E | G5: 2027E | H5: 2028E | I5: 2029E | J5: 2030E | K5: 2031E | L5: 2032E | M5: 2033E | N5: 2034E | O5: 2035E
B7: Revenue | C7: =_CapIQ_Data!C31 -> 383285 | D7: =_CapIQ_Data!D31 -> 391035 | E7: =_CapIQ_Data!E31 -> 416161 | F7: =E7*(1+F8) -> 436969.05 | G7: =F7*(1+G8) -> 458817.5 | H7: =G7*(1+H8) -> 481758.38 | I7: =H7*(1+I8) -> 505846.3 | J7: =I7*(1+J8) -> 531138.61 | K7: =J7*(1+K8) -> 557695.54 | L7: =K7*(1+L8) -> 585580.32 | M7: =L7*(1+M8) -> 614859.33 | ... O7: =N7*(1+O8) -> 677882.42
B8: % Growth | D8: =D7/C7-1 -> 0.020219941 | E8: =E7/D7-1 -> 0.064255118 | F8: =Inputs!I$31 -> 0.05 | G8: =Inputs!J$31 -> 0.05 | H8: =Inputs!K$31 -> 0.05 | I8: =Inputs!L$31 -> 0.05 | J8: =Inputs!M$31 -> 0.05 | K8: =Inputs!N$31 -> 0.05 | L8: =Inputs!O$31 -> 0.05 | M8: =Inputs!P$31 -> 0.05 | ... O8: =Inputs!R$31 -> 0.05
B10: (–) COGS | C10: =_CapIQ_Data!C32*-1 -> -214137 | D10: =_CapIQ_Data!D32*-1 -> -210352 | E10: =_CapIQ_Data!E32*-1 -> -220960 | F10: =F11-F7 -> -262181.43 | G10: =G11-G7 -> -275290.5 | H10: =H11-H7 -> -289055.03 | I10: =I11-I7 -> -303507.78 | J10: =J11-J7 -> -318683.17 | K10: =K11-K7 -> -334617.33 | L10: =L11-L7 -> -351348.19 | M10: =M11-M7 -> -368915.6 | ... O10: =O11-O7 -> -406729.45
B11: Gross Profit | C11: =SUM(C10,C7) -> 169148 | D11: =SUM(D10,D7) -> 180683 | E11: =SUM(E10,E7) -> 195201 | F11: =F12*F7 -> 174787.62 | G11: =G12*G7 -> 183527 | H11: =H12*H7 -> 192703.35 | I11: =I12*I7 -> 202338.52 | J11: =J12*J7 -> 212455.44 | K11: =K12*K7 -> 223078.22 | L11: =L12*L7 -> 234232.13 | M11: =M12*M7 -> 245943.73 | ... O11: =O12*O7 -> 271152.97
B12: % Gross Margin | C12: =IFERROR(C11/C7,0) -> 0.4413113 | D12: =IFERROR(D11/D7,0) -> 0.4620635 | E12: =IFERROR(E11/E7,0) -> 0.46905164 | F12: =Inputs!I$32 -> 0.4 | G12: =Inputs!J$32 -> 0.4 | H12: =Inputs!K$32 -> 0.4 | I12: =Inputs!L$32 -> 0.4 | J12: =Inputs!M$32 -> 0.4 | K12: =Inputs!N$32 -> 0.4 | L12: =Inputs!O$32 -> 0.4 | M12: =Inputs!P$32 -> 0.4 | ... O12: =Inputs!R$32 -> 0.4
B14: (–) Opex | C14: =_CapIQ_Data!C34*-1 -> -54847 | D14: =_CapIQ_Data!D34*-1 -> -57467 | E14: =_CapIQ_Data!E34*-1 -> -62151 | F14: =F16-F15 -> -68607.372 | G14: =G16-G15 -> -74812.655 | H14: =H16-H15 -> -81605.694 | I14: =I16-I15 -> -89043.626 | J14: =J16-J15 -> -97189.219 | K14: =K16-K15 -> -106111.43 | L14: =L16-L15 -> -115886.03 | M14: =M16-M15 -> -126596.27 | ... O14: =O16-O15 -> -151198.56
B15: (+) D&A | C15: =C24*-1 -> 11519 | D15: =D24*-1 -> 11445 | E15: =E24*-1 -> 11698 | F15: =F24*-1 -> 13109.072 | G15: =G24*-1 -> 13764.525 | H15: =H24*-1 -> 14452.751 | I15: =I24*-1 -> 15175.389 | J15: =J24*-1 -> 15934.158 | ... O15: =O24*-1 -> 20336.473
B16: (–) Cash Opex | C16: =SUM(C14:C15) -> -43328 | D16: =SUM(D14:D15) -> -46022 | E16: =SUM(E14:E15) -> -50453 | F16: =E16*(1+F18) -> -55498.3 | G16: =F16*(1+G18) -> -61048.13 | H16: =G16*(1+H18) -> -67152.943 | I16: =H16*(1+I18) -> -73868.237 | J16: =I16*(1+J18) -> -81255.061 | K16: =J16*(1+K18) -> -89380.567 | L16: =K16*(1+L18) -> -98318.624 | M16: =L16*(1+M18) -> -108150.49 | ... O16: =N16*(1+O18) -> -130862.09
B17: % Revenue | C17: =C16/C7*-1 -> 0.11304382 | D17: =D16/D7*-1 -> 0.11769279 | E17: =E16/E7*-1 -> 0.12123433 | F17: =F16/F7*-1 -> 0.12700739 | G17: =G16/G7*-1 -> 0.13305536 | H17: =H16/H7*-1 -> 0.13939133 | I17: =I16/I7*-1 -> 0.14602902 | J17: =J16/J7*-1 -> 0.15298278 | ... O17: =O16/O7*-1 -> 0.19304541
B18: % Growth | D18: =D16/C16-1 -> 0.062176883 | E18: =E16/D16-1 -> 0.09628004 | F18: =Inputs!I$33 -> 0.1 | G18: =Inputs!J$33 -> 0.1 | H18: =Inputs!K$33 -> 0.1 | I18: =Inputs!L$33 -> 0.1 | J18: =Inputs!M$33 -> 0.1 | K18: =Inputs!N$33 -> 0.1 | L18: =Inputs!O$33 -> 0.1 | M18: =Inputs!P$33 -> 0.1 | ... O18: =Inputs!R$33 -> 0.1
B20: EBITDA | C20: =SUM(C16,C11) -> 125820 | D20: =SUM(D16,D11) -> 134661 | E20: =SUM(E16,E11) -> 144748 | F20: =SUM(F16,F11) -> 119289.32 | G20: =SUM(G16,G11) -> 122478.87 | H20: =SUM(H16,H11) -> 125550.41 | I20: =SUM(I16,I11) -> 128470.28 | J20: =SUM(J16,J11) -> 131200.38 | ... O20: =SUM(O16,O11) -> 140290.88
B21: % Margin | C21: =IFERROR(C20/C7,0) -> 0.32826748 | D21: =IFERROR(D20/D7,0) -> 0.34437071 | E21: =IFERROR(E20/E7,0) -> 0.34781731 | F21: =IFERROR(F20/F7,0) -> 0.27299261 | G21: =IFERROR(G20/G7,0) -> 0.26694464 | H21: =IFERROR(H20/H7,0) -> 0.26060867 | I21: =IFERROR(I20/I7,0) -> 0.25397098 | J21: =IFERROR(J20/J7,0) -> 0.24701722 | ... O21: =IFERROR(O20/O7,0) -> 0.20695459
B22: % Growth | D22: =D20/C20-1 -> 0.070267048 | E22: =E20/D20-1 -> 0.074906617 | F22: =F20/E20-1 -> -0.17588278 | G22: =G20/F20-1 -> 0.026737943 | H22: =H20/G20-1 -> 0.025078097 | I22: =I20/H20-1 -> 0.023256581 | J22: =J20/I20-1 -> 0.021250846 | K22: =K20/J20-1 -> 0.019033985 | ... O22: =O20/N20-1 -> 0.0072912564
B24: (–) D&A | C24: =_CapIQ_Data!C35*-1 -> -11519 | D24: =_CapIQ_Data!D35*-1 -> -11445 | E24: =_CapIQ_Data!E35*-1 -> -11698 | F24: =F25*F46*-1 -> -13109.072 | G24: =G25*G46*-1 -> -13764.525 | H24: =H25*H46*-1 -> -14452.751 | I24: =I25*I46*-1 -> -15175.389 | J24: =J25*J46*-1 -> -15934.158 | K24: =K25*K46*-1 -> -16730.866 | L24: =L25*L46*-1 -> -17567.41 | M24: =M25*M46*-1 -> -18445.78 | ... O24: =O25*O46*-1 -> -20336.473
B25: D&A % Capex | C25: =C24/C46*-1 -> 1.0510996 | D25: =D24/D46*-1 -> 1.2114957 | E25: =E24/E46*-1 -> 0.92001573 | F25: =Inputs!I$36 -> 1 | G25: =Inputs!J$36 -> 1 | H25: =Inputs!K$36 -> 1 | I25: =Inputs!L$36 -> 1 | J25: =Inputs!M$36 -> 1 | K25: =Inputs!N$36 -> 1 | L25: =Inputs!O$36 -> 1 | M25: =Inputs!P$36 -> 1 | ... O25: =Inputs!R$36 -> 1
B26: (–) SBC | C26: =_CapIQ_Data!C39*-1 -> -10833 | D26: =_CapIQ_Data!D39*-1 -> -11688 | E26: =_CapIQ_Data!E39*-1 -> -12863 | F26: =F27*F16 -> -13874.575 | G26: =G27*G16 -> -15262.033 | H26: =H27*H16 -> -16788.236 | I26: =I27*I16 -> -18467.059 | J26: =J27*J16 -> -20313.765 | K26: =K27*K16 -> -22345.142 | L26: =L27*L16 -> -24579.656 | M26: =M27*M16 -> -27037.622 | ... O26: =O27*O16 -> -32715.522
B27: SBC % Cash Opex | C27: =C26/C16 -> 0.25002308 | D27: =D26/D16 -> 0.25396549 | E27: =E26/E16 -> 0.25495015 | F27: =Inputs!I34 -> 0.25 | G27: =Inputs!J34 -> 0.25 | H27: =Inputs!K34 -> 0.25 | I27: =Inputs!L34 -> 0.25 | J27: =Inputs!M34 -> 0.25 | K27: =Inputs!N34 -> 0.25 | L27: =Inputs!O34 -> 0.25 | M27: =Inputs!P34 -> 0.25 | ... O27: =Inputs!R34 -> 0.25
B29: EBIT | C29: =SUM(C24,C20,C26) -> 103468 | D29: =SUM(D24,D20,D26) -> 111528 | E29: =SUM(E24,E20,E26) -> 120187 | F29: =SUM(F24,F20,F26) -> 92305.674 | G29: =SUM(G24,G20,G26) -> 93452.313 | H29: =SUM(H24,H20,H26) -> 94309.421 | I29: =SUM(I24,I20,I26) -> 94827.833 | J29: =SUM(J24,J20,J26) -> 94952.46 | ... O29: =SUM(O24,O20,O26) -> 87238.884
B30: % Margin | C30: =IFERROR(C29/C7,0) -> 0.26995056 | D30: =IFERROR(D29/D7,0) -> 0.28521232 | E30: =IFERROR(E29/E7,0) -> 0.28879929 | F30: =IFERROR(F29/F7,0) -> 0.21124076 | G30: =IFERROR(G29/G7,0) -> 0.20368079 | H30: =IFERROR(H29/H7,0) -> 0.19576083 | I30: =IFERROR(I29/I7,0) -> 0.18746373 | J30: =IFERROR(J29/J7,0) -> 0.17877153 | ... O30: =IFERROR(O29/O7,0) -> 0.12869324
B31: % Growth | D31: =D29/C29-1 -> 0.077898481 | E31: =E29/D29-1 -> 0.077639696 | F31: =F29/E29-1 -> -0.23198288 | G31: =G29/F29-1 -> 0.012422204 | H31: =H29/G29-1 -> 0.0091716033 | I31: =I29/H29-1 -> 0.0054969282 | J31: =J29/I29-1 -> 0.0013142431 | K31: =K29/J29-1 -> -0.0034840416 | ... O31: =O29/N29-1 -> -0.032462918
B33: (–) Net Interest Expense | F33: =IFERROR(Debt!F33,0) -> 0 | G33: =IFERROR(Debt!G33,0) -> 0 | H33: =IFERROR(Debt!H33,0) -> 0 | I33: =IFERROR(Debt!I33,0) -> 0 | J33: =IFERROR(Debt!J33,0) -> 0 | K33: =IFERROR(Debt!K33,0) -> 0 | L33: =IFERROR(Debt!L33,0) -> 0 | M33: =IFERROR(Debt!M33,0) -> 0 | ... O33: =IFERROR(Debt!O33,0) -> 0
B34: Pre-tax Income | F34: =SUM(F33,F29) -> 92305.674 | G34: =SUM(G33,G29) -> 93452.313 | H34: =SUM(H33,H29) -> 94309.421 | I34: =SUM(I33,I29) -> 94827.833 | J34: =SUM(J33,J29) -> 94952.46 | K34: =SUM(K33,K29) -> 94621.642 | L34: =SUM(L33,L29) -> 93766.438 | M34: =SUM(M33,M29) -> 92309.846 | ... O34: =SUM(O33,O29) -> 87238.884
B36: (–) Taxes | F36: =F37*F34*-1 -> -24922.532 | G36: =G37*G34*-1 -> -25232.125 | H36: =H37*H34*-1 -> -25463.544 | I36: =I37*I34*-1 -> -25603.515 | J36: =J37*J34*-1 -> -25637.164 | K36: =K37*K34*-1 -> -25547.843 | L36: =L37*L34*-1 -> -25316.938 | M36: =M37*M34*-1 -> -24923.658 | ... O36: =O37*O34*-1 -> -23554.499
B37: % Tax Rate | F37: =inp_tax_rate -> 0.27 | G37: =inp_tax_rate -> 0.27 | H37: =inp_tax_rate -> 0.27 | I37: =inp_tax_rate -> 0.27 | J37: =inp_tax_rate -> 0.27 | K37: =inp_tax_rate -> 0.27 | L37: =inp_tax_rate -> 0.27 | M37: =inp_tax_rate -> 0.27 | ... O37: =inp_tax_rate -> 0.27
B39: Net Income | F39: =F34-F36 -> 117228.21 | G39: =G34-G36 -> 118684.44 | H39: =H34-H36 -> 119772.96 | I39: =I34-I36 -> 120431.35 | J39: =J34-J36 -> 120589.62 | K39: =K34-K36 -> 120169.48 | L39: =L34-L36 -> 119083.38 | M39: =M34-M36 -> 117233.5 | ... O39: =O34-O36 -> 110793.38
B41: (÷) DSO | F41: =inp_diluted_shares -> 14681.14 | G41: =inp_diluted_shares -> 14681.14 | H41: =inp_diluted_shares -> 14681.14 | I41: =inp_diluted_shares -> 14681.14 | J41: =inp_diluted_shares -> 14681.14 | K41: =inp_diluted_shares -> 14681.14 | L41: =inp_diluted_shares -> 14681.14 | M41: =inp_diluted_shares -> 14681.14 | ... O41: =inp_diluted_shares -> 14681.14
B42: Diluted EPS | F42: =IFERROR(F39/F41,0) -> 7.9849525 | G42: =IFERROR(G39/G41,0) -> 8.0841432 | H42: =IFERROR(H39/H41,0) -> 8.1582878 | I42: =IFERROR(I39/I41,0) -> 8.2031333 | J42: =IFERROR(J39/J41,0) -> 8.2139142 | K42: =IFERROR(K39/K41,0) -> 8.1852966 | L42: =IFERROR(L39/L41,0) -> 8.1113167 | M42: =IFERROR(M39/M41,0) -> 7.9853134 | ... O42: =IFERROR(O39/O41,0) -> 7.5466471
B43: % Growth | G43: =G42/F42-1 -> 0.012422204 | H43: =H42/G42-1 -> 0.0091716033 | I43: =I42/H42-1 -> 0.0054969282 | J43: =J42/I42-1 -> 0.0013142431 | K43: =K42/J42-1 -> -0.0034840416 | L43: =L42/K42-1 -> -0.0090381371 | M43: =M42/L42-1 -> -0.015534258 | N43: =N42/M42-1 -> -0.023225183 | O43: =O42/N42-1 -> -0.032462918
B45: Memo:
B46: Capex | C46: =_CapIQ_Data!C38*-1 -> 10959 | D46: =_CapIQ_Data!D38*-1 -> 9447 | E46: =_CapIQ_Data!E38*-1 -> 12715 | F46: =F47*F7 -> 13109.072 | G46: =G47*G7 -> 13764.525 | H46: =H47*H7 -> 14452.751 | I46: =I47*I7 -> 15175.389 | J46: =J47*J7 -> 15934.158 | K46: =K47*K7 -> 16730.866 | L46: =L47*L7 -> 17567.41 | M46: =M47*M7 -> 18445.78 | ... O46: =O47*O7 -> 20336.473
B47: Capex % Revenue | C47: =C46/C7 -> 0.028592301 | D47: =D46/D7 -> 0.024158963 | E47: =E46/E7 -> 0.030553079 | F47: =Inputs!I35 -> 0.03 | G47: =Inputs!J35 -> 0.03 | H47: =Inputs!K35 -> 0.03 | I47: =Inputs!L35 -> 0.03 | J47: =Inputs!M35 -> 0.03 | K47: =Inputs!N35 -> 0.03 | L47: =Inputs!O35 -> 0.03 | M47: =Inputs!P35 -> 0.03 | ... O47: =Inputs!R35 -> 0.03

Sheet CF
B2: =inp_ticker & " | Levered Free Cash Flow" -> APPL | Levered Free Cash Flow
C4: Actual | F4: Forecast
C5: 2023A | D5: 2024A | E5: 2025A | F5: 2026E | G5: 2027E | H5: 2028E | I5: 2029E | J5: 2030E | K5: 2031E | L5: 2032E | M5: 2033E | N5: 2034E | O5: 2035E
B7: EBITDA | C7: =IS!C20 -> 125820 | D7: =IS!D20 -> 134661 | E7: =IS!E20 -> 144748 | F7: =IS!F20 -> 119289.32 | G7: =IS!G20 -> 122478.87 | H7: =IS!H20 -> 125550.41 | I7: =IS!I20 -> 128470.28 | J7: =IS!J20 -> 131200.38 | ... O7: =IS!O20 -> 140290.88
B8: (–) Cash Taxes | F8: =IS!F36 -> -24922.532 | G8: =IS!G36 -> -25232.125 | H8: =IS!H36 -> -25463.544 | I8: =IS!I36 -> -25603.515 | J8: =IS!J36 -> -25637.164 | K8: =IS!K36 -> -25547.843 | L8: =IS!L36 -> -25316.938 | M8: =IS!M36 -> -24923.658 | ... O8: =IS!O36 -> -23554.499
B9: (–) Cash Interest | F9: =IS!F33 -> 0 | G9: =IS!G33 -> 0 | H9: =IS!H33 -> 0 | I9: =IS!I33 -> 0 | J9: =IS!J33 -> 0 | K9: =IS!K33 -> 0 | L9: =IS!L33 -> 0 | M9: =IS!M33 -> 0 | ... O9: =IS!O33 -> 0
B10: (–) Capex | F10: =IS!F46*-1 -> -13109.072 | G10: =IS!G46*-1 -> -13764.525 | H10: =IS!H46*-1 -> -14452.751 | I10: =IS!I46*-1 -> -15175.389 | J10: =IS!J46*-1 -> -15934.158 | K10: =IS!K46*-1 -> -16730.866 | L10: =IS!L46*-1 -> -17567.41 | M10: =IS!M46*-1 -> -18445.78 | ... O10: =IS!O46*-1 -> -20336.473
B11: Levered Free Cash Flow | F11: =SUM(F7:F10) -> 81257.717 | G11: =SUM(G7:G10) -> 83482.221 | H11: =SUM(H7:H10) -> 85634.113 | I11: =SUM(I7:I10) -> 87691.377 | J11: =SUM(J7:J10) -> 89629.061 | K11: =SUM(K7:K10) -> 91418.94 | L11: =SUM(L7:L10) -> 93029.156 | M11: =SUM(M7:M10) -> 94423.809 | ... O11: =SUM(O7:O10) -> 96399.907
B12: (–) Debt Amortization | F12: =IFERROR(-(Debt!F34+Debt!F35),0) -> 0 | G12: =IFERROR(-(Debt!G34+Debt!G35),0) -> 0 | H12: =IFERROR(-(Debt!H34+Debt!H35),0) -> 0 | I12: =IFERROR(-(Debt!I34+Debt!I35),0) -> 0 | J12: =IFERROR(-(Debt!J34+Debt!J35),0) -> 0 | K12: =IFERROR(-(Debt!K34+Debt!K35),0) -> 0 | L12: =IFERROR(-(Debt!L34+Debt!L35),0) -> 0 | M12: =IFERROR(-(Debt!M34+Debt!M35),0) -> 0 | ... O12: =IFERROR(-(Debt!O34+Debt!O35),0) -> 0
B13: (–) Dividends | F13: =-inp_annual_dps*((1+inp_dps_growth)^0)*IS!F41 -> -14974.763 | G13: =-inp_annual_dps*((1+inp_dps_growth)^1)*IS!G41 -> -14974.763 | H13: =-inp_annual_dps*((1+inp_dps_growth)^2)*IS!H41 -> -14974.763 | I13: =-inp_annual_dps*((1+inp_dps_growth)^3)*IS!I41 -> -14974.763 | J13: =-inp_annual_dps*((1+inp_dps_growth)^4)*IS!J41 -> -14974.763 | K13: =-inp_annual_dps*((1+inp_dps_growth)^5)*IS!K41 -> -14974.763 | L13: =-inp_annual_dps*((1+inp_dps_growth)^6)*IS!L41 -> -14974.763 | M13: =-inp_annual_dps*((1+inp_dps_growth)^7)*IS!M41 -> -14974.763 | N13: =-inp_annual_dps*((1+inp_dps_growth)^8)*IS!N41 -> -14974.763 | O13: =-inp_annual_dps*((1+inp_dps_growth)^9)*IS!O41 -> -14974.763
B14: Net Change in Cash | F14: =SUM(F11:F13) -> 66282.954 | G14: =SUM(G11:G13) -> 68507.459 | H14: =SUM(H11:H13) -> 70659.35 | I14: =SUM(I11:I13) -> 72716.615 | J14: =SUM(J11:J13) -> 74654.298 | K14: =SUM(K11:K13) -> 76444.177 | L14: =SUM(L11:L13) -> 78054.393 | M14: =SUM(M11:M13) -> 79449.046 | ... O14: =SUM(O11:O13) -> 81425.144
B16: Beginning Cash | F16: =E18 -> 45317 | G16: =F18 -> 111599.95 | H16: =G18 -> 180107.41 | I16: =H18 -> 250766.76 | J16: =I18 -> 323483.38 | K16: =J18 -> 398137.68 | L16: =K18 -> 474581.85 | M16: =L18 -> 552636.25 | ... O16: =N18 -> 712673.04
B17: (+/–) Change in Cash | F17: =F14 -> 66282.954 | G17: =G14 -> 68507.459 | H17: =H14 -> 70659.35 | I17: =I14 -> 72716.615 | J17: =J14 -> 74654.298 | K17: =K14 -> 76444.177 | L17: =L14 -> 78054.393 | M17: =M14 -> 79449.046 | ... O17: =O14 -> 81425.144
B18: Ending Cash | E18: =inp_cash -> 45317 | F18: =SUM(F16:F17) -> 111599.95 | G18: =SUM(G16:G17) -> 180107.41 | H18: =SUM(H16:H17) -> 250766.76 | I18: =SUM(I16:I17) -> 323483.38 | J18: =SUM(J16:J17) -> 398137.68 | K18: =SUM(K16:K17) -> 474581.85 | L18: =SUM(L16:L17) -> 552636.25 | M18: =SUM(M16:M17) -> 632085.29 | ... O18: =SUM(O16:O17) -> 794098.19

Sheet Debt
B2: =inp_ticker & " | Debt Schedule" -> APPL | Debt Schedule
C4: 2023A | D4: 2024A | E4: 2025A | F4: 2026E | G4: 2027E | H4: 2028E | I4: 2029E | J4: 2030E | K4: 2031E | L4: 2032E | M4: 2033E | N4: 2034E | O4: 2035E
B5: Revolver
B6: Beginning Balance | C6: 0 | D6: =C9 -> 0 | E6: =D9 -> 0 | F6: =E9 -> 0 | G6: =F9 -> 0 | H6: =G9 -> 0 | I6: =H9 -> 0 | J6: =I9 -> 0 | K6: =J9 -> 0 | ... O6: =N9 -> 0
B7: Draws | C7: 0 | D7: 0 | E7: 0 | F7: 0 | G7: 0 | H7: 0 | I7: 0 | J7: 0 | K7: 0 | L7: 0 | M7: 0 | N7: 0 | O7: 0
B8: Repayments | C8: 0 | D8: 0 | E8: 0 | F8: 0 | G8: 0 | H8: 0 | I8: 0 | J8: 0 | K8: 0 | L8: 0 | M8: 0 | N8: 0 | O8: 0
B9: Ending Balance | C9: =C6+C7-C8 -> 0 | D9: =D6+D7-D8 -> 0 | E9: =E6+E7-E8 -> 0 | F9: =F6+F7-F8 -> 0 | G9: =G6+G7-G8 -> 0 | H9: =H6+H7-H8 -> 0 | I9: =I6+I7-I8 -> 0 | J9: =J6+J7-J8 -> 0 | ... O9: =O6+O7-O8 -> 0
B10: Average Balance | C10: =(C6+C9)/2 -> 0 | D10: =(D6+D9)/2 -> 0 | E10: =(E6+E9)/2 -> 0 | F10: =(F6+F9)/2 -> 0 | G10: =(G6+G9)/2 -> 0 | H10: =(H6+H9)/2 -> 0 | I10: =(I6+I9)/2 -> 0 | J10: =(J6+J9)/2 -> 0 | ... O10: =(O6+O9)/2 -> 0
B11: Interest Rate % | C11: 0.06 | D11: 0.06 | E11: 0.06 | F11: 0.06 | G11: 0.06 | H11: 0.06 | I11: 0.06 | J11: 0.06 | K11: 0.06 | L11: 0.06 | M11: 0.06 | N11: 0.06 | O11: 0.06
B12: Interest Expense | C12: =C10*C11 -> 0 | D12: =D10*D11 -> 0 | E12: =E10*E11 -> 0 | F12: =F10*F11 -> 0 | G12: =G10*G11 -> 0 | H12: =H10*H11 -> 0 | I12: =I10*I11 -> 0 | J12: =J10*J11 -> 0 | ... O12: =O10*O11 -> 0
B14: Term Loan
B15: Beginning Balance | C15: 0 | D15: =C18 -> 0 | E15: =D18 -> 0 | F15: =E18 -> 0 | G15: =F18 -> 0 | H15: =G18 -> 0 | I15: =H18 -> 0 | J15: =I18 -> 0 | K15: =J18 -> 0 | ... O15: =N18 -> 0
B16: Mandatory Amortization | C16: 0 | D16: 0 | E16: 0 | F16: 0 | G16: 0 | H16: 0 | I16: 0 | J16: 0 | K16: 0 | L16: 0 | M16: 0 | N16: 0 | O16: 0
B17: Optional Prepayment (Cash Sweep) | C17: 0 | D17: 0 | E17: 0 | F17: =F40 -> 0 | G17: =G40 -> 0 | H17: =H40 -> 0 | I17: =I40 -> 0 | J17: =J40 -> 0 | K17: =K40 -> 0 | L17: =L40 -> 0 | M17: =M40 -> 0 | ... O17: =O40 -> 0
B18: Ending Balance | C18: =C15-C16-C17 -> 0 | D18: =D15-D16-D17 -> 0 | E18: =E15-E16-E17 -> 0 | F18: =F15-F16-F17 -> 0 | G18: =G15-G16-G17 -> 0 | H18: =H15-H16-H17 -> 0 | I18: =I15-I16-I17 -> 0 | J18: =J15-J16-J17 -> 0 | ... O18: =O15-O16-O17 -> 0
B19: Average Balance | C19: =(C15+C18)/2 -> 0 | D19: =(D15+D18)/2 -> 0 | E19: =(E15+E18)/2 -> 0 | F19: =(F15+F18)/2 -> 0 | G19: =(G15+G18)/2 -> 0 | H19: =(H15+H18)/2 -> 0 | I19: =(I15+I18)/2 -> 0 | J19: =(J15+J18)/2 -> 0 | ... O19: =(O15+O18)/2 -> 0
B20: Interest Rate % | C20: 0.07 | D20: 0.07 | E20: 0.07 | F20: 0.07 | G20: 0.07 | H20: 0.07 | I20: 0.07 | J20: 0.07 | K20: 0.07 | L20: 0.07 | M20: 0.07 | N20: 0.07 | O20: 0.07
B21: Interest Expense | C21: =C19*C20 -> 0 | D21: =D19*D20 -> 0 | E21: =E19*E20 -> 0 | F21: =F19*F20 -> 0 | G21: =G19*G20 -> 0 | H21: =H19*H20 -> 0 | I21: =I19*I20 -> 0 | J21: =J19*J20 -> 0 | ... O21: =O19*O20 -> 0
B23: Senior Notes
B24: Beginning Balance | C24: 0 | D24: =C26 -> 0 | E24: =D26 -> 0 | F24: =E26 -> 0 | G24: =F26 -> 0 | H24: =G26 -> 0 | I24: =H26 -> 0 | J24: =I26 -> 0 | K24: =J26 -> 0 | ... O24: =N26 -> 0
B25: Repayment at Maturity | C25: 0 | D25: 0 | E25: 0 | F25: 0 | G25: 0 | H25: 0 | I25: 0 | J25: 0 | K25: 0 | L25: 0 | M25: 0 | N25: 0 | O25: 0
B26: Ending Balance | C26: =C24-C25 -> 0 | D26: =D24-D25 -> 0 | E26: =E24-E25 -> 0 | F26: =F24-F25 -> 0 | G26: =G24-G25 -> 0 | H26: =H24-H25 -> 0 | I26: =I24-I25 -> 0 | J26: =J24-J25 -> 0 | ... O26: =O24-O25 -> 0
B27: Interest Rate % | C27: 0.05 | D27: 0.05 | E27: 0.05 | F27: 0.05 | G27: 0.05 | H27: 0.05 | I27: 0.05 | J27: 0.05 | K27: 0.05 | L27: 0.05 | M27: 0.05 | N27: 0.05 | O27: 0.05
B28: Interest Expense | C28: =C24*C27 -> 0 | D28: =D24*D27 -> 0 | E28: =E24*E27 -> 0 | F28: =F24*F27 -> 0 | G28: =G24*G27 -> 0 | H28: =H24*H27 -> 0 | I28: =I24*I27 -> 0 | J28: =J24*J27 -> 0 | ... O28: =O24*O27 -> 0
B30: Totals
B31: Total Beginning Debt | C31: =C6+C15+C24 -> 0 | D31: =D6+D15+D24 -> 0 | E31: =E6+E15+E24 -> 0 | F31: =F6+F15+F24 -> 0 | G31: =G6+G15+G24 -> 0 | H31: =H6+H15+H24 -> 0 | I31: =I6+I15+I24 -> 0 | J31: =J6+J15+J24 -> 0 | ... O31: =O6+O15+O24 -> 0
B32: Total Ending Debt | C32: =C9+C18+C26 -> 0 | D32: =D9+D18+D26 -> 0 | E32: =E9+E18+E26 -> 0 | F32: =F9+F18+F26 -> 0 | G32: =G9+G18+G26 -> 0 | H32: =H9+H18+H26 -> 0 | I32: =I9+I18+I26 -> 0 | J32: =J9+J18+J26 -> 0 | ... O32: =O9+O18+O26 -> 0
B33: Total Interest Expense | C33: =C12+C21+C28 -> 0 | D33: =D12+D21+D28 -> 0 | E33: =E12+E21+E28 -> 0 | F33: =F12+F21+F28 -> 0 | G33: =G12+G21+G28 -> 0 | H33: =H12+H21+H28 -> 0 | I33: =I12+I21+I28 -> 0 | J33: =J12+J21+J28 -> 0 | ... O33: =O12+O21+O28 -> 0
B34: Total Mandatory Amortization | C34: =C16 -> 0 | D34: =D16 -> 0 | E34: =E16 -> 0 | F34: =F16 -> 0 | G34: =G16 -> 0 | H34: =H16 -> 0 | I34: =I16 -> 0 | J34: =J16 -> 0 | ... O34: =O16 -> 0
B35: Total Optional Prepayment | C35: =C17 -> 0 | D35: =D17 -> 0 | E35: =E17 -> 0 | F35: =F17 -> 0 | G35: =G17 -> 0 | H35: =H17 -> 0 | I35: =I17 -> 0 | J35: =J17 -> 0 | ... O35: =O17 -> 0
B37: Cash Sweep
B38: Available Cash for Sweep | C38: 0 | D38: 0 | E38: 0 | F38: =MAX(0,CF!F18-inp_min_cash) -> 111599.95 | G38: =MAX(0,CF!G18-inp_min_cash) -> 180107.41 | H38: =MAX(0,CF!H18-inp_min_cash) -> 250766.76 | I38: =MAX(0,CF!I18-inp_min_cash) -> 323483.38 | J38: =MAX(0,CF!J18-inp_min_cash) -> 398137.68 | K38: =MAX(0,CF!K18-inp_min_cash) -> 474581.85 | L38: =MAX(0,CF!L18-inp_min_cash) -> 552636.25 | M38: =MAX(0,CF!M18-inp_min_cash) -> 632085.29 | ... O38: =MAX(0,CF!O18-inp_min_cash) -> 794098.19
B39: Cash Sweep Applied | C39: 0 | D39: 0 | E39: 0 | F39: =F38*inp_cash_sweep_pct -> 0 | G39: =G38*inp_cash_sweep_pct -> 0 | H39: =H38*inp_cash_sweep_pct -> 0 | I39: =I38*inp_cash_sweep_pct -> 0 | J39: =J38*inp_cash_sweep_pct -> 0 | K39: =K38*inp_cash_sweep_pct -> 0 | L39: =L38*inp_cash_sweep_pct -> 0 | M39: =M38*inp_cash_sweep_pct -> 0 | ... O39: =O38*inp_cash_sweep_pct -> 0
B40: Allocated to Term Loan | C40: 0 | D40: 0 | E40: 0 | F40: =F39 -> 0 | G40: =G39 -> 0 | H40: =H39 -> 0 | I40: =I39 -> 0 | J40: =J39 -> 0 | K40: =K39 -> 0 | L40: =L39 -> 0 | M40: =M39 -> 0 | ... O40: =O39 -> 0

Sheet Valuation
B2: =inp_ticker & " | Valuation" -> APPL | Valuation
F4: 2026E | G4: 2027E | H4: 2028E | I4: 2029E | J4: 2030E | K4: 2031E | L4: 2032E | M4: 2033E | N4: 2034E | O4: 2035E
B5: Year-end EBITDA | F5: =IS!F20 -> 119289.32 | G5: =IS!G20 -> 122478.87 | H5: =IS!H20 -> 125550.41 | I5: =IS!I20 -> 128470.28 | J5: =IS!J20 -> 131200.38 | K5: =IS!K20 -> 133697.65 | L5: =IS!L20 -> 135913.5 | M5: =IS!M20 -> 137793.25 | ... O5: =IS!O20 -> 140290.88
B6: Exit EBITDA Multiple | F6: =Inputs!I$37 -> 10 | G6: =Inputs!J$37 -> 10 | H6: =Inputs!K$37 -> 10 | I6: =Inputs!L$37 -> 10 | J6: =Inputs!M$37 -> 10 | K6: =Inputs!N$37 -> 10 | L6: =Inputs!O$37 -> 10 | M6: =Inputs!P$37 -> 10 | ... O6: =Inputs!R$37 -> 10
B7: Implied Enterprise Value | F7: =F5*F6 -> 1192893.2 | G7: =G5*G6 -> 1224788.7 | H7: =H5*H6 -> 1255504.1 | I7: =I5*I6 -> 1284702.8 | J7: =J5*J6 -> 1312003.8 | K7: =K5*K6 -> 1336976.5 | L7: =L5*L6 -> 1359135 | M7: =M5*M6 -> 1377932.5 | ... O7: =O5*O6 -> 1402908.8
B8: (Less) Year-end Total Debt | F8: =-Debt!F32 -> 0 | G8: =-Debt!G32 -> 0 | H8: =-Debt!H32 -> 0 | I8: =-Debt!I32 -> 0 | J8: =-Debt!J32 -> 0 | K8: =-Debt!K32 -> 0 | L8: =-Debt!L32 -> 0 | M8: =-Debt!M32 -> 0 | ... O8: =-Debt!O32 -> 0
B9: Plus: Year-end Cash | F9: =CF!F18 -> 111599.95 | G9: =CF!G18 -> 180107.41 | H9: =CF!H18 -> 250766.76 | I9: =CF!I18 -> 323483.38 | J9: =CF!J18 -> 398137.68 | K9: =CF!K18 -> 474581.85 | L9: =CF!L18 -> 552636.25 | M9: =CF!M18 -> 632085.29 | ... O9: =CF!O18 -> 794098.19
B10: (Less) Minority Interest | F10: =-inp_minority_interest -> 0 | G10: =-inp_minority_interest -> 0 | H10: =-inp_minority_interest -> 0 | I10: =-inp_minority_interest -> 0 | J10: =-inp_minority_interest -> 0 | K10: =-inp_minority_interest -> 0 | L10: =-inp_minority_interest -> 0 | M10: =-inp_minority_interest -> 0 | ... O10: =-inp_minority_interest -> 0
B11: Plus: Equity Investments | F11: =inp_equity_investments -> 0 | G11: =inp_equity_investments -> 0 | H11: =inp_equity_investments -> 0 | I11: =inp_equity_investments -> 0 | J11: =inp_equity_investments -> 0 | K11: =inp_equity_investments -> 0 | L11: =inp_equity_investments -> 0 | M11: =inp_equity_investments -> 0 | ... O11: =inp_equity_investments -> 0
B12: Implied Equity Value | F12: =F7+F8+F9+F10+F11 -> 1304493.2 | G12: =G7+G8+G9+G10+G11 -> 1404896.1 | H12: =H7+H8+H9+H10+H11 -> 1506270.8 | I12: =I7+I8+I9+I10+I11 -> 1608186.2 | J12: =J7+J8+J9+J10+J11 -> 1710141.5 | K12: =K7+K8+K9+K10+K11 -> 1811558.3 | L12: =L7+L8+L9+L10+L11 -> 1911771.3 | M12: =M7+M8+M9+M10+M11 -> 2010017.8 | ... O12: =O7+O8+O9+O10+O11 -> 2197007
B13: / Diluted Shares Outstanding | F13: =IS!F41 -> 14681.14 | G13: =IS!G41 -> 14681.14 | H13: =IS!H41 -> 14681.14 | I13: =IS!I41 -> 14681.14 | J13: =IS!J41 -> 14681.14 | K13: =IS!K41 -> 14681.14 | L13: =IS!L41 -> 14681.14 | M13: =IS!M41 -> 14681.14 | ... O13: =IS!O41 -> 14681.14
B14: Implied Price per Share | F14: =IFERROR(F12/F13,0) -> 88.855031 | G14: =IFERROR(G12/G13,0) -> 95.693939 | H14: =IFERROR(H12/H13,0) -> 102.59904 | I14: =IFERROR(I12/I13,0) -> 109.54096 | J14: =IFERROR(J12/J13,0) -> 116.48561 | K14: =IFERROR(K12/K13,0) -> 123.39357 | L14: =IFERROR(L12/L13,0) -> 130.21954 | M14: =IFERROR(M12/M13,0) -> 136.91156 | ... O14: =IFERROR(O12/O13,0) -> 149.64825
B15: Implied IRR from Today | F15: =IFERROR((F14/inp_current_price)^(1/1)-1,0) -> -0.6679682 | G15: =IFERROR((G14/inp_current_price)^(1/2)-1,0) -> -0.40201396 | H15: =IFERROR((H14/inp_current_price)^(1/3)-1,0) -> -0.27353675 | I15: =IFERROR((I14/inp_current_price)^(1/4)-1,0) -> -0.20013158 | J15: =IFERROR((J14/inp_current_price)^(1/5)-1,0) -> -0.15325238 | K15: =IFERROR((K14/inp_current_price)^(1/6)-1,0) -> -0.12104825 | L15: =IFERROR((L14/inp_current_price)^(1/7)-1,0) -> -0.097783958 | M15: =IFERROR((M14/inp_current_price)^(1/8)-1,0) -> -0.080361335 | N15: =IFERROR((N14/inp_current_price)^(1/9)-1,0) -> -0.066965804 | O15: =IFERROR((O14/inp_current_price)^(1/10)-1,0) -> -0.056467353
B16: Implied MOIC | F16: =IFERROR(F14/inp_current_price,0) -> 0.3320318 | G16: =IFERROR(G14/inp_current_price,0) -> 0.35758731 | H16: =IFERROR(H14/inp_current_price,0) -> 0.38339015 | I16: =IFERROR(I14/inp_current_price,0) -> 0.4093306 | J16: =IFERROR(J14/inp_current_price,0) -> 0.43528122 | K16: =IFERROR(K14/inp_current_price,0) -> 0.46109478 | L16: =IFERROR(L14/inp_current_price,0) -> 0.48660192 | M16: =IFERROR(M14/inp_current_price,0) -> 0.51160853 | ... O16: =IFERROR(O14/inp_current_price,0) -> 0.55920277

Sheet Summary
B2: =inp_ticker & " | Summary" -> APPL | Summary
B4: Company Name | C4: =inp_company_name -> Apple Inc.
B5: Ticker | C5: =inp_ticker -> APPL
B6: Sector | C6: =inp_sector -> Information Technology
B8: Financial Summary
C9: 2023A | D9: 2024A | E9: 2025A | F9: 2026E | G9: 2027E | H9: 2028E | I9: 2029E | J9: 2030E | K9: 2031E | L9: 2032E | M9: 2033E | N9: 2034E | O9: 2035E
B10: Revenue | C10: =IS!C7 -> 383285 | D10: =IS!D7 -> 391035 | E10: =IS!E7 -> 416161 | F10: =IS!F7 -> 436969.05 | G10: =IS!G7 -> 458817.5 | H10: =IS!H7 -> 481758.38 | I10: =IS!I7 -> 505846.3 | J10: =IS!J7 -> 531138.61 | ... O10: =IS!O7 -> 677882.42
B11: Revenue Growth % | C11: =IS!C8 -> 0 | D11: =IS!D8 -> 0.020219941 | E11: =IS!E8 -> 0.064255118 | F11: =IS!F8 -> 0.05 | G11: =IS!G8 -> 0.05 | H11: =IS!H8 -> 0.05 | I11: =IS!I8 -> 0.05 | J11: =IS!J8 -> 0.05 | ... O11: =IS!O8 -> 0.05
B12: EBITDA | C12: =IS!C20 -> 125820 | D12: =IS!D20 -> 134661 | E12: =IS!E20 -> 144748 | F12: =IS!F20 -> 119289.32 | G12: =IS!G20 -> 122478.87 | H12: =IS!H20 -> 125550.41 | I12: =IS!I20 -> 128470.28 | J12: =IS!J20 -> 131200.38 | ... O12: =IS!O20 -> 140290.88
B13: EBITDA Margin % | C13: =IS!C21 -> 0.32826748 | D13: =IS!D21 -> 0.34437071 | E13: =IS!E21 -> 0.34781731 | F13: =IS!F21 -> 0.27299261 | G13: =IS!G21 -> 0.26694464 | H13: =IS!H21 -> 0.26060867 | I13: =IS!I21 -> 0.25397098 | J13: =IS!J21 -> 0.24701722 | ... O13: =IS!O21 -> 0.20695459
B14: Levered Free Cash Flow | C14: =CF!C11 -> 0 | D14: =CF!D11 -> 0 | E14: =CF!E11 -> 0 | F14: =CF!F11 -> 81257.717 | G14: =CF!G11 -> 83482.221 | H14: =CF!H11 -> 85634.113 | I14: =CF!I11 -> 87691.377 | J14: =CF!J11 -> 89629.061 | ... O14: =CF!O11 -> 96399.907
B15: LFCF Margin % | C15: =IFERROR(C14/C10,0) -> 0 | D15: =IFERROR(D14/D10,0) -> 0 | E15: =IFERROR(E14/E10,0) -> 0 | F15: =IFERROR(F14/F10,0) -> 0.1859576 | G15: =IFERROR(G14/G10,0) -> 0.18195082 | H15: =IFERROR(H14/H10,0) -> 0.17775324 | I15: =IFERROR(I14/I10,0) -> 0.17335578 | J15: =IFERROR(J14/J10,0) -> 0.16874891 | ... O15: =IFERROR(O14/O10,0) -> 0.14220742
B16: Net Debt | C16: =Debt!C32-CF!C18 -> 0 | D16: =Debt!D32-CF!D18 -> 0 | E16: =Debt!E32-CF!E18 -> -45317 | F16: =Debt!F32-CF!F18 -> -111599.95 | G16: =Debt!G32-CF!G18 -> -180107.41 | H16: =Debt!H32-CF!H18 -> -250766.76 | I16: =Debt!I32-CF!I18 -> -323483.38 | J16: =Debt!J32-CF!J18 -> -398137.68 | ... O16: =Debt!O32-CF!O18 -> -794098.19
B17: Net Leverage (Net Debt / EBITDA) | C17: =IFERROR(C16/C12,0) -> 0 | D17: =IFERROR(D16/D12,0) -> 0 | E17: =IFERROR(E16/E12,0) -> -0.31307514 | F17: =IFERROR(F16/F12,0) -> -0.9355402 | G17: =IFERROR(G16/G12,0) -> -1.4705182 | H17: =IFERROR(H16/H12,0) -> -1.9973393 | I17: =IFERROR(I16/I12,0) -> -2.5179627 | J17: =IFERROR(J16/J12,0) -> -3.0345771 | ... O17: =IFERROR(O16/O12,0) -> -5.6603694
B19: Returns Table
B20: Year | C20: Implied Price per Share | D20: Implied IRR | E20: Implied MOIC
B21: Y1 (2026E) | C21: =Valuation!F14 -> 88.855031 | D21: =Valuation!F15 -> -0.6679682 | E21: =Valuation!F16 -> 0.3320318
B22: Y3 (2028E) | C22: =Valuation!H14 -> 102.59904 | D22: =Valuation!H15 -> -0.27353675 | E22: =Valuation!H16 -> 0.38339015
B23: Y5 (2030E) | C23: =Valuation!J14 -> 116.48561 | D23: =Valuation!J15 -> -0.15325238 | E23: =Valuation!J16 -> 0.43528122
B24: Y10 (2035E) | C24: =Valuation!O14 -> 149.64825 | D24: =Valuation!O15 -> -0.056467353 | E24: =Valuation!O16 -> 0.55920277

Sheet Sensitivity
B2: =inp_ticker & " | Sensitivity" -> APPL | Sensitivity
B4: Target Year Offset (1 = first projection year) | C4: 5
B6: Exit Multiple | C6: ="Implied Price per Share at Year " & sens_target_year_offset -> Implied Price per Share at Year 5
B7: 6 | C7: =(INDEX(IS!$F$20:$O$20,sens_target_year_offset)*$B7-INDEX(Debt!$F$32:$O$32,sens_target_year_offset)+INDEX(CF!$F$18:$O$18,sens_target_year_offset)-inp_minority_interest+inp_equity_investments)/INDEX(IS!$F$41:$O$41,sens_target_year_offset) -> 80.73896
B8: 7 | C8: =(INDEX(IS!$F$20:$O$20,sens_target_year_offset)*$B8-INDEX(Debt!$F$32:$O$32,sens_target_year_offset)+INDEX(CF!$F$18:$O$18,sens_target_year_offset)-inp_minority_interest+inp_equity_investments)/INDEX(IS!$F$41:$O$41,sens_target_year_offset) -> 89.675622
B9: 8 | C9: =(INDEX(IS!$F$20:$O$20,sens_target_year_offset)*$B9-INDEX(Debt!$F$32:$O$32,sens_target_year_offset)+INDEX(CF!$F$18:$O$18,sens_target_year_offset)-inp_minority_interest+inp_equity_investments)/INDEX(IS!$F$41:$O$41,sens_target_year_offset) -> 98.612284
B10: 9 | C10: =(INDEX(IS!$F$20:$O$20,sens_target_year_offset)*$B10-INDEX(Debt!$F$32:$O$32,sens_target_year_offset)+INDEX(CF!$F$18:$O$18,sens_target_year_offset)-inp_minority_interest+inp_equity_investments)/INDEX(IS!$F$41:$O$41,sens_target_year_offset) -> 107.54895
B11: 10 | C11: =(INDEX(IS!$F$20:$O$20,sens_target_year_offset)*$B11-INDEX(Debt!$F$32:$O$32,sens_target_year_offset)+INDEX(CF!$F$18:$O$18,sens_target_year_offset)-inp_minority_interest+inp_equity_investments)/INDEX(IS!$F$41:$O$41,sens_target_year_offset) -> 116.48561
B12: 11 | C12: =(INDEX(IS!$F$20:$O$20,sens_target_year_offset)*$B12-INDEX(Debt!$F$32:$O$32,sens_target_year_offset)+INDEX(CF!$F$18:$O$18,sens_target_year_offset)-inp_minority_interest+inp_equity_investments)/INDEX(IS!$F$41:$O$41,sens_target_year_offset) -> 125.42227
B13: 12 | C13: =(INDEX(IS!$F$20:$O$20,sens_target_year_offset)*$B13-INDEX(Debt!$F$32:$O$32,sens_target_year_offset)+INDEX(CF!$F$18:$O$18,sens_target_year_offset)-inp_minority_interest+inp_equity_investments)/INDEX(IS!$F$41:$O$41,sens_target_year_offset) -> 134.35893
B14: 13 | C14: =(INDEX(IS!$F$20:$O$20,sens_target_year_offset)*$B14-INDEX(Debt!$F$32:$O$32,sens_target_year_offset)+INDEX(CF!$F$18:$O$18,sens_target_year_offset)-inp_minority_interest+inp_equity_investments)/INDEX(IS!$F$41:$O$41,sens_target_year_offset) -> 143.29559
B15: 14 | C15: =(INDEX(IS!$F$20:$O$20,sens_target_year_offset)*$B15-INDEX(Debt!$F$32:$O$32,sens_target_year_offset)+INDEX(CF!$F$18:$O$18,sens_target_year_offset)-inp_minority_interest+inp_equity_investments)/INDEX(IS!$F$41:$O$41,sens_target_year_offset) -> 152.23225
B17: 2D Sensitivity (Exit Multiple x Year)
B18: Multiple | C18: Y3 | D18: Y5 | E18: Y7 | F18: Y10
B19: 6 | C19: =(INDEX(IS!$F$20:$O$20,3)*$B19-INDEX(Debt!$F$32:$O$32,3)+INDEX(CF!$F$18:$O$18,3)-inp_minority_interest+inp_equity_investments)/INDEX(IS!$F$41:$O$41,3) -> 68.391774 | D19: =(INDEX(IS!$F$20:$O$20,5)*$B19-INDEX(Debt!$F$32:$O$32,5)+INDEX(CF!$F$18:$O$18,5)-inp_minority_interest+inp_equity_investments)/INDEX(IS!$F$41:$O$41,5) -> 80.73896 | E19: =(INDEX(IS!$F$20:$O$20,7)*$B19-INDEX(Debt!$F$32:$O$32,7)+INDEX(CF!$F$18:$O$18,7)-inp_minority_interest+inp_equity_investments)/INDEX(IS!$F$41:$O$41,7) -> 93.188762 | F19: =(INDEX(IS!$F$20:$O$20,10)*$B19-INDEX(Debt!$F$32:$O$32,10)+INDEX(CF!$F$18:$O$18,10)-inp_minority_interest+inp_equity_investments)/INDEX(IS!$F$41:$O$41,10) -> 111.42483
B20: 7 | C20: =(INDEX(IS!$F$20:$O$20,3)*$B20-INDEX(Debt!$F$32:$O$32,3)+INDEX(CF!$F$18:$O$18,3)-inp_minority_interest+inp_equity_investments)/INDEX(IS!$F$41:$O$41,3) -> 76.94359 | D20: =(INDEX(IS!$F$20:$O$20,5)*$B20-INDEX(Debt!$F$32:$O$32,5)+INDEX(CF!$F$18:$O$18,5)-inp_minority_interest+inp_equity_investments)/INDEX(IS!$F$41:$O$41,5) -> 89.675622 | E20: =(INDEX(IS!$F$20:$O$20,7)*$B20-INDEX(Debt!$F$32:$O$32,7)+INDEX(CF!$F$18:$O$18,7)-inp_minority_interest+inp_equity_investments)/INDEX(IS!$F$41:$O$41,7) -> 102.44646 | F20: =(INDEX(IS!$F$20:$O$20,10)*$B20-INDEX(Debt!$F$32:$O$32,10)+INDEX(CF!$F$18:$O$18,10)-inp_minority_interest+inp_equity_investments)/INDEX(IS!$F$41:$O$41,10) -> 120.98068
B21: 8 | C21: =(INDEX(IS!$F$20:$O$20,3)*$B21-INDEX(Debt!$F$32:$O$32,3)+INDEX(CF!$F$18:$O$18,3)-inp_minority_interest+inp_equity_investments)/INDEX(IS!$F$41:$O$41,3) -> 85.495406 | D21: =(INDEX(IS!$F$20:$O$20,5)*$B21-INDEX(Debt!$F$32:$O$32,5)+INDEX(CF!$F$18:$O$18,5)-inp_minority_interest+inp_equity_investments)/INDEX(IS!$F$41:$O$41,5) -> 98.612284 | E21: =(INDEX(IS!$F$20:$O$20,7)*$B21-INDEX(Debt!$F$32:$O$32,7)+INDEX(CF!$F$18:$O$18,7)-inp_minority_interest+inp_equity_investments)/INDEX(IS!$F$41:$O$41,7) -> 111.70415 | F21: =(INDEX(IS!$F$20:$O$20,10)*$B21-INDEX(Debt!$F$32:$O$32,10)+INDEX(CF!$F$18:$O$18,10)-inp_minority_interest+inp_equity_investments)/INDEX(IS!$F$41:$O$41,10) -> 130.53654
B22: 9 | C22: =(INDEX(IS!$F$20:$O$20,3)*$B22-INDEX(Debt!$F$32:$O$32,3)+INDEX(CF!$F$18:$O$18,3)-inp_minority_interest+inp_equity_investments)/INDEX(IS!$F$41:$O$41,3) -> 94.047222 | D22: =(INDEX(IS!$F$20:$O$20,5)*$B22-INDEX(Debt!$F$32:$O$32,5)+INDEX(CF!$F$18:$O$18,5)-inp_minority_interest+inp_equity_investments)/INDEX(IS!$F$41:$O$41,5) -> 107.54895 | E22: =(INDEX(IS!$F$20:$O$20,7)*$B22-INDEX(Debt!$F$32:$O$32,7)+INDEX(CF!$F$18:$O$18,7)-inp_minority_interest+inp_equity_investments)/INDEX(IS!$F$41:$O$41,7) -> 120.96184 | F22: =(INDEX(IS!$F$20:$O$20,10)*$B22-INDEX(Debt!$F$32:$O$32,10)+INDEX(CF!$F$18:$O$18,10)-inp_minority_interest+inp_equity_investments)/INDEX(IS!$F$41:$O$41,10) -> 140.0924
B23: 10 | C23: =(INDEX(IS!$F$20:$O$20,3)*$B23-INDEX(Debt!$F$32:$O$32,3)+INDEX(CF!$F$18:$O$18,3)-inp_minority_interest+inp_equity_investments)/INDEX(IS!$F$41:$O$41,3) -> 102.59904 | D23: =(INDEX(IS!$F$20:$O$20,5)*$B23-INDEX(Debt!$F$32:$O$32,5)+INDEX(CF!$F$18:$O$18,5)-inp_minority_interest+inp_equity_investments)/INDEX(IS!$F$41:$O$41,5) -> 116.48561 | E23: =(INDEX(IS!$F$20:$O$20,7)*$B23-INDEX(Debt!$F$32:$O$32,7)+INDEX(CF!$F$18:$O$18,7)-inp_minority_interest+inp_equity_investments)/INDEX(IS!$F$41:$O$41,7) -> 130.21954 | F23: =(INDEX(IS!$F$20:$O$20,10)*$B23-INDEX(Debt!$F$32:$O$32,10)+INDEX(CF!$F$18:$O$18,10)-inp_minority_interest+inp_equity_investments)/INDEX(IS!$F$41:$O$41,10) -> 149.64825
B24: 11 | C24: =(INDEX(IS!$F$20:$O$20,3)*$B24-INDEX(Debt!$F$32:$O$32,3)+INDEX(CF!$F$18:$O$18,3)-inp_minority_interest+inp_equity_investments)/INDEX(IS!$F$41:$O$41,3) -> 111.15085 | D24: =(INDEX(IS!$F$20:$O$20,5)*$B24-INDEX(Debt!$F$32:$O$32,5)+INDEX(CF!$F$18:$O$18,5)-inp_minority_interest+inp_equity_investments)/INDEX(IS!$F$41:$O$41,5) -> 125.42227 | E24: =(INDEX(IS!$F$20:$O$20,7)*$B24-INDEX(Debt!$F$32:$O$32,7)+INDEX(CF!$F$18:$O$18,7)-inp_minority_interest+inp_equity_investments)/INDEX(IS!$F$41:$O$41,7) -> 139.47723 | F24: =(INDEX(IS!$F$20:$O$20,10)*$B24-INDEX(Debt!$F$32:$O$32,10)+INDEX(CF!$F$18:$O$18,10)-inp_minority_interest+inp_equity_investments)/INDEX(IS!$F$41:$O$41,10) -> 159.20411
B25: 12 | C25: =(INDEX(IS!$F$20:$O$20,3)*$B25-INDEX(Debt!$F$32:$O$32,3)+INDEX(CF!$F$18:$O$18,3)-inp_minority_interest+inp_equity_investments)/INDEX(IS!$F$41:$O$41,3) -> 119.70267 | D25: =(INDEX(IS!$F$20:$O$20,5)*$B25-INDEX(Debt!$F$32:$O$32,5)+INDEX(CF!$F$18:$O$18,5)-inp_minority_interest+inp_equity_investments)/INDEX(IS!$F$41:$O$41,5) -> 134.35893 | E25: =(INDEX(IS!$F$20:$O$20,7)*$B25-INDEX(Debt!$F$32:$O$32,7)+INDEX(CF!$F$18:$O$18,7)-inp_minority_interest+inp_equity_investments)/INDEX(IS!$F$41:$O$41,7) -> 148.73493 | F25: =(INDEX(IS!$F$20:$O$20,10)*$B25-INDEX(Debt!$F$32:$O$32,10)+INDEX(CF!$F$18:$O$18,10)-inp_minority_interest+inp_equity_investments)/INDEX(IS!$F$41:$O$41,10) -> 168.75997
B26: 13 | C26: =(INDEX(IS!$F$20:$O$20,3)*$B26-INDEX(Debt!$F$32:$O$32,3)+INDEX(CF!$F$18:$O$18,3)-inp_minority_interest+inp_equity_investments)/INDEX(IS!$F$41:$O$41,3) -> 128.25449 | D26: =(INDEX(IS!$F$20:$O$20,5)*$B26-INDEX(Debt!$F$32:$O$32,5)+INDEX(CF!$F$18:$O$18,5)-inp_minority_interest+inp_equity_investments)/INDEX(IS!$F$41:$O$41,5) -> 143.29559 | E26: =(INDEX(IS!$F$20:$O$20,7)*$B26-INDEX(Debt!$F$32:$O$32,7)+INDEX(CF!$F$18:$O$18,7)-inp_minority_interest+inp_equity_investments)/INDEX(IS!$F$41:$O$41,7) -> 157.99262 | F26: =(INDEX(IS!$F$20:$O$20,10)*$B26-INDEX(Debt!$F$32:$O$32,10)+INDEX(CF!$F$18:$O$18,10)-inp_minority_interest+inp_equity_investments)/INDEX(IS!$F$41:$O$41,10) -> 178.31583
B27: 14 | C27: =(INDEX(IS!$F$20:$O$20,3)*$B27-INDEX(Debt!$F$32:$O$32,3)+INDEX(CF!$F$18:$O$18,3)-inp_minority_interest+inp_equity_investments)/INDEX(IS!$F$41:$O$41,3) -> 136.8063 | D27: =(INDEX(IS!$F$20:$O$20,5)*$B27-INDEX(Debt!$F$32:$O$32,5)+INDEX(CF!$F$18:$O$18,5)-inp_minority_interest+inp_equity_investments)/INDEX(IS!$F$41:$O$41,5) -> 152.23225 | E27: =(INDEX(IS!$F$20:$O$20,7)*$B27-INDEX(Debt!$F$32:$O$32,7)+INDEX(CF!$F$18:$O$18,7)-inp_minority_interest+inp_equity_investments)/INDEX(IS!$F$41:$O$41,7) -> 167.25032 | F27: =(INDEX(IS!$F$20:$O$20,10)*$B27-INDEX(Debt!$F$32:$O$32,10)+INDEX(CF!$F$18:$O$18,10)-inp_minority_interest+inp_equity_investments)/INDEX(IS!$F$41:$O$41,10) -> 187.87168

Sheet _CapIQ_Data
B2: =inp_ticker & " | CapIQ Data" -> APPL | CapIQ Data
B4: _CapIQ_Data — DO NOT EDIT MANUALLY. Populated by shared/fetch_capiq.py.
B5: Run via: | C5: python -m shared.fetch_capiq <TICKER>
B6: Ticker: | C6: AAPL
B7: Date | C7: 46139
B8: Fetcher Run-Date | C8: 46022
B10: Field | C10: IQ_FY-2 | D10: IQ_FY-1 | E10: IQ_FY | F10: Current
B12: Company Name | F12: Apple Inc.
B13: Sector | F13: Information Technology
B14: Currency | F14: USD
B15: Filing Status | F15: Operating
B18: Current Price | F18: 267.61
B19: Diluted Shares Out | F19: 14681.14
B20: Market Cap | F20: =F18*F19 -> 3928819.9
B21: Cash & Equivalents | F21: 45317
B22: ST Investments | F22: 21590
B23: Total Debt | F23: 90509
B24: Preferred Equity | F24: 0
B25: Minority Interest | F25: 0
B26: Equity Investments | F26: 0
B27: Marketable Securities | F27: 77888
B28: Enterprise Value | F28: =F20-F21-F22+F23+F24+F25-F26-F27 -> 3874533.9
B31: Revenue | C31: 383285 | D31: 391035 | E31: 416161
B32: COGS | C32: 214137 | D32: 210352 | E32: 220960
B33: Gross Profit | C33: 169148 | D33: 180683 | E33: 195201
B34: Total Opex | C34: 54847 | D34: 57467 | E34: 62151
B35: D&A | C35: 11519 | D35: 11445 | E35: 11698
B36: EBITDA | C36: 125820 | D36: 134661 | E36: 144748
B37: EBIT | C37: 114301 | D37: 123216 | E37: 133050
B38: Capex | C38: -10959 | D38: -9447 | E38: -12715
B39: SBC | C39: 10833 | D39: 11688 | E39: 12863
B40: DPS | C40: 0.94 | D40: 0.98 | E40: 1.02

Sheet _Broker_Data
B2: =inp_ticker & " | Broker Data" -> APPL | Broker Data
B4: _Broker_Data — DO NOT EDIT MANUALLY. Populated by shared/fetch_broker_estimates.py.
B5: Last fetch:
B6: Ticker:
B7: FY1 fiscal year:
B8: FY2 fiscal year:
B9: FY3 fiscal year:
B11: Field | C11: FY1 Mean | D11: FY2 Mean | E11: FY3 Mean | F11: FY1 High | G11: FY1 Low | H11: FY1 # Est
B13: Revenue
B14: Gross Profit
B15: EBITDA
B16: EBIT
B17: Net Income
B18: EPS (Diluted)
B19: CFO
B20: CapEx
B23: Revenue Growth FY1 % | C23: =IFERROR(C13/_CapIQ_Data!E31-1,"") -> -1
B24: Revenue Growth FY2 % | C24: =IFERROR(D13/C13-1,"")
B25: Revenue Growth FY3 % | C25: =IFERROR(E13/D13-1,"")
B26: Gross Margin FY1 % | C26: =IFERROR(C14/C13,"")
B27: EBITDA Margin FY1 % | C27: =IFERROR(C15/C13,"")
B28: EBIT Margin FY1 % | C28: =IFERROR(C16/C13,"")
B31: Number of Analysts Covering
B32: Average Price Target
B33: Implied Upside % | C33: =IFERROR(C32/inp_current_price-1,"") -> -1
B34: Average Recommendation (1=Buy,5=Sell)
B35: Recommendation Distribution
